carbonize/__init__.py
carbonize/api.py
carbonize/calculators/__init__.py
carbonize/calculators/base.py
carbonize/calculators/cars.py
carbonize/calculators/flights.py
carbonize/calculators/trains.py
carbonize/calculators/webinars.py
carbonize/catalogs.py
carbonize/data/__init__.py
carbonize/data/iata_airports.pkl
carbonize/data/icao_aircrafts.pkl
carbonize/data/icao_load_factors.pkl
carbonize/data/parsers/__init__.py
carbonize/data/parsers/iata_parser.py
carbonize/data/parsers/icao_parser.py
carbonize/py.typed
carbonize/type_definitions.py
carbonize/utils.py
carbonize-0.1.0.dist-info/LICENSE
carbonize-0.1.0.dist-info/METADATA
carbonize-0.1.0.dist-info/WHEEL
carbonize-0.1.0.dist-info/RECORD
